slidercracker/__init__.py
slidercracker-0.1.1.dist-info/LICENSE
slidercracker-0.1.1.dist-info/METADATA
slidercracker-0.1.1.dist-info/WHEEL
slidercracker-0.1.1.dist-info/top_level.txt
slidercracker-0.1.1.dist-info/RECORD
