Metadata-Version: 2.1
Name: slidercracker
Version: 0.1.1
Summary: make it easy to crack slider
Home-page: https://gitee.com/ZeroSeeker/slidercracker
Author: ZeroSeeker
Author-email: zeroseeker@foxmail.com
Classifier: Programming Language :: Python :: 3
Classifier: License :: OSI Approved :: MIT License
Classifier: Operating System :: OS Independent
License-File: LICENSE
Requires-Dist: lazysdk >=0.1.87
Requires-Dist: opencv-python >=4.5.5.64
Requires-Dist: ddddocr >=1.4.7
